multistate/__init__.py
multistate/core/__init__.py
multistate/core/element.py
multistate/core/state.py
multistate/core/state_group.py
multistate/dynamics/hidden_states.py
multistate/manager.py
multistate/pathfinding/__init__.py
multistate/pathfinding/multi_target.py
multistate/pathfinding/visualizer.py
multistate/transitions/__init__.py
multistate/transitions/callbacks.py
multistate/transitions/executor.py
multistate/transitions/transition.py
multistate-0.1.1.dist-info/licenses/LICENSE
multistate-0.1.1.dist-info/METADATA
multistate-0.1.1.dist-info/WHEEL
multistate-0.1.1.dist-info/RECORD
