Metadata-Version: 2.4
Name: multistate
Version: 0.1.1
Summary: A Python library for managing multiple simultaneous active states with intelligent pathfinding and coordinated transitions
License: MIT
License-File: LICENSE
Keywords: state-machine,fsm,multi-state,pathfinding,gui-automation,state-management,transitions
Author: Joshua Spinak
Author-email: jspinak@alum.mit.edu
Requires-Python: >=3.10,<4.0
Classifier: Development Status :: 3 - Alpha
Classifier: Intended Audience :: Developers
Classifier: License :: OSI Approved :: MIT License
Classifier: Programming Language :: Python :: 3
Classifier: Programming Language :: Python :: 3.10
Classifier: Programming Language :: Python :: 3.11
Classifier: Programming Language :: Python :: 3.12
Classifier: Programming Language :: Python :: 3.13
Classifier: Programming Language :: Python :: 3.14
Classifier: Topic :: Software Development :: Libraries :: Python Modules
Requires-Dist: dataclasses-json (>=0.6.0)
Requires-Dist: typing-extensions (>=4.0.0)
Project-URL: Documentation, https://jspinak.github.io/multistate/
Project-URL: Homepage, https://github.com/qontinui/multistate
Project-URL: Repository, https://github.com/qontinui/multistate
